pipeit/__init__.py
pipeit/base.py
pipeit/io.py
pipeit/io_base.py
pipeit/timer.py
pipeit/timer_archive.py
pipeit/utils.py
pipeit/wrapper.py
pipeit-0.3.4.dist-info/LICENSE
pipeit-0.3.4.dist-info/METADATA
pipeit-0.3.4.dist-info/WHEEL
pipeit-0.3.4.dist-info/top_level.txt
pipeit-0.3.4.dist-info/RECORD
