Metadata-Version: 2.1
Name: pipeit
Version: 0.3.4
Summary: Syntax suger for python's functional programming as Unix pipes. - GoodManWEN/pipeit
Home-page: https://github.com/GoodManWEN/pipeit
Author: WEN
License: UNKNOWN
Keywords: pipeit
Platform: UNKNOWN
Classifier: Programming Language :: Python :: 3
Classifier: Programming Language :: Python :: 3.8
Classifier: Programming Language :: Python :: 3.9
Classifier: Programming Language :: Python :: 3.10
Classifier: Programming Language :: Python :: 3.11
Classifier: Programming Language :: Python :: 3.12
Classifier: License :: OSI Approved :: MIT License
Classifier: Operating System :: POSIX :: Linux
Classifier: Operating System :: Microsoft :: Windows
Requires-Python: >=3.6
